[
    {
        "name": "To Do",
        "cards": [
            { "name": "Card A1" },
            { "name": "Card A2" },
            { "name": "Card A3" }
        ] 
    },
    {
        "name": "In Progress",
        "cards": [
            { "name": "Card B1" },
            { "name": "Card B2" },
            { "name": "Card B3" }
        ] 
    },
    {
        "name": "Done",
        "cards": [
            { "name": "Card C1" },
            { "name": "Card C2" },
            { "name": "Card C3" }
        ] 
    }    
]